ninja-1.11.1.1.dist-info/top_level.txt
ninja-1.11.1.1.dist-info/WHEEL
ninja-1.11.1.1.dist-info/METADATA
ninja-1.11.1.1.dist-info/LICENSE_Apache_20
ninja-1.11.1.1.dist-info/AUTHORS.rst
ninja-1.11.1.1.dist-info/entry_points.txt
ninja/py.typed
ninja/__init__.py
ninja/_version.py
ninja/__main__.py
ninja/ninja_syntax.py
ninja/data/bin/ninja
ninja-1.11.1.1.dist-info/RECORD
