Metadata-Version: 2.1
Name: ninja
Version: 1.11.1.1
Summary: Ninja is a small build system with a focus on speed
Home-page: http://ninja-build.org/
Download-URL: https://github.com/ninja-build/ninja/releases
Author: Jean-Christophe Fillion-Robin
Author-email: scikit-build@googlegroups.com
License: Apache 2.0
Project-URL: Documentation, https://github.com/scikit-build/ninja-python-distributions#readme
Project-URL: Source Code, https://github.com/scikit-build/ninja-python-distributions
Project-URL: Mailing list, https://groups.google.com/forum/#!forum/scikit-build
Project-URL: Bug Tracker, https://github.com/scikit-build/ninja-python-distributions/issues
Keywords: ninja build c++ fortran cross-platform cross-compilation
Classifier: License :: OSI Approved :: Apache Software License
Classifier: License :: OSI Approved :: BSD License
Classifier: Programming Language :: C
Classifier: Programming Language :: C++
Classifier: Programming Language :: Fortran
Classifier: Programming Language :: Python
Classifier: Operating System :: OS Independent
Classifier: Development Status :: 5 - Production/Stable
Classifier: Intended Audience :: Developers
Classifier: Topic :: Software Development :: Build Tools
Classifier: Typing :: Typed
License-File: LICENSE_Apache_20
License-File: AUTHORS.rst
Provides-Extra: test
Requires-Dist: codecov>=2.0.5; extra == "test"
Requires-Dist: coverage>=4.2; extra == "test"
Requires-Dist: flake8>=3.0.4; extra == "test"
Requires-Dist: pytest>=4.5.0; extra == "test"
Requires-Dist: pytest-cov>=2.7.1; extra == "test"
Requires-Dist: pytest-runner>=5.1; extra == "test"
Requires-Dist: pytest-virtualenv>=1.7.0; extra == "test"
Requires-Dist: virtualenv>=15.0.3; extra == "test"
